{
    "docID": "dxDrawer",
    "className": "DxDrawer",
    "widgetName": "dxDrawer",
    "isTranscludedContent": true,
    "isViz": false,
    "isExtension": false,
    "selector": "dx-drawer",
    "events": [
        {
            "docID": "dxDrawerOptions.onDisposing",
            "emit": "onDisposing",
            "subscribe": "disposing",
            "type": "EventEmitter<DisposingEvent>"
        },
        {
            "docID": "dxDrawerOptions.onInitialized",
            "emit": "onInitialized",
            "subscribe": "initialized",
            "type": "EventEmitter<InitializedEvent>"
        },
        {
            "docID": "dxDrawerOptions.onOptionChanged",
            "emit": "onOptionChanged",
            "subscribe": "optionChanged",
            "type": "EventEmitter<OptionChangedEvent>"
        },
        {
            "isInternal": true,
            "emit": "activeStateEnabledChange",
            "type": "EventEmitter<boolean>"
        },
        {
            "isInternal": true,
            "emit": "animationDurationChange",
            "type": "EventEmitter<number>"
        },
        {
            "isInternal": true,
            "emit": "animationEnabledChange",
            "type": "EventEmitter<boolean>"
        },
        {
            "isInternal": true,
            "emit": "closeOnOutsideClickChange",
            "type": "EventEmitter<boolean | Function>"
        },
        {
            "isInternal": true,
            "emit": "disabledChange",
            "type": "EventEmitter<boolean>"
        },
        {
            "isInternal": true,
            "emit": "elementAttrChange",
            "type": "EventEmitter<any>"
        },
        {
            "isInternal": true,
            "emit": "heightChange",
            "type": "EventEmitter<number | Function | string | undefined>"
        },
        {
            "isInternal": true,
            "emit": "hintChange",
            "type": "EventEmitter<string | undefined>"
        },
        {
            "isInternal": true,
            "emit": "hoverStateEnabledChange",
            "type": "EventEmitter<boolean>"
        },
        {
            "isInternal": true,
            "emit": "maxSizeChange",
            "type": "EventEmitter<number>"
        },
        {
            "isInternal": true,
            "emit": "minSizeChange",
            "type": "EventEmitter<number>"
        },
        {
            "isInternal": true,
            "emit": "openedChange",
            "type": "EventEmitter<boolean>"
        },
        {
            "isInternal": true,
            "emit": "openedStateModeChange",
            "type": "EventEmitter<string>"
        },
        {
            "isInternal": true,
            "emit": "positionChange",
            "type": "EventEmitter<string>"
        },
        {
            "isInternal": true,
            "emit": "revealModeChange",
            "type": "EventEmitter<string>"
        },
        {
            "isInternal": true,
            "emit": "rtlEnabledChange",
            "type": "EventEmitter<boolean>"
        },
        {
            "isInternal": true,
            "emit": "shadingChange",
            "type": "EventEmitter<boolean>"
        },
        {
            "isInternal": true,
            "emit": "templateChange",
            "type": "EventEmitter<any>"
        },
        {
            "isInternal": true,
            "emit": "visibleChange",
            "type": "EventEmitter<boolean>"
        },
        {
            "isInternal": true,
            "emit": "widthChange",
            "type": "EventEmitter<number | Function | string | undefined>"
        }
    ],
    "properties": [
        {
            "docID": "WidgetOptions.activeStateEnabled",
            "name": "activeStateEnabled",
            "type": "boolean",
            "typesDescription": {
                "primitiveTypes": [
                    "boolean"
                ],
                "arrayTypes": []
            }
        },
        {
            "docID": "dxDrawerOptions.animationDuration",
            "name": "animationDuration",
            "type": "number",
            "typesDescription": {
                "primitiveTypes": [
                    "number"
                ],
                "arrayTypes": []
            }
        },
        {
            "docID": "dxDrawerOptions.animationEnabled",
            "name": "animationEnabled",
            "type": "boolean",
            "typesDescription": {
                "primitiveTypes": [
                    "boolean"
                ],
                "arrayTypes": []
            }
        },
        {
            "docID": "dxDrawerOptions.closeOnOutsideClick",
            "name": "closeOnOutsideClick",
            "type": "boolean | Function",
            "typesDescription": {
                "primitiveTypes": [
                    "boolean",
                    "Function"
                ],
                "arrayTypes": []
            }
        },
        {
            "docID": "WidgetOptions.disabled",
            "name": "disabled",
            "type": "boolean",
            "typesDescription": {
                "primitiveTypes": [
                    "boolean"
                ],
                "arrayTypes": []
            }
        },
        {
            "docID": "DOMComponentOptions.elementAttr",
            "name": "elementAttr",
            "type": "any",
            "typesDescription": {
                "primitiveTypes": [
                    "any"
                ],
                "arrayTypes": []
            }
        },
        {
            "docID": "DOMComponentOptions.height",
            "name": "height",
            "type": "number | Function | string | undefined",
            "typesDescription": {
                "primitiveTypes": [
                    "number",
                    "Function",
                    "string",
                    "undefined"
                ],
                "arrayTypes": []
            }
        },
        {
            "docID": "WidgetOptions.hint",
            "name": "hint",
            "type": "string | undefined",
            "typesDescription": {
                "primitiveTypes": [
                    "string",
                    "undefined"
                ],
                "arrayTypes": []
            }
        },
        {
            "docID": "WidgetOptions.hoverStateEnabled",
            "name": "hoverStateEnabled",
            "type": "boolean",
            "typesDescription": {
                "primitiveTypes": [
                    "boolean"
                ],
                "arrayTypes": []
            }
        },
        {
            "docID": "dxDrawerOptions.maxSize",
            "name": "maxSize",
            "type": "number",
            "typesDescription": {
                "primitiveTypes": [
                    "number"
                ],
                "arrayTypes": []
            }
        },
        {
            "docID": "dxDrawerOptions.minSize",
            "name": "minSize",
            "type": "number",
            "typesDescription": {
                "primitiveTypes": [
                    "number"
                ],
                "arrayTypes": []
            }
        },
        {
            "docID": "dxDrawerOptions.opened",
            "name": "opened",
            "type": "boolean",
            "typesDescription": {
                "primitiveTypes": [
                    "boolean"
                ],
                "arrayTypes": []
            }
        },
        {
            "docID": "dxDrawerOptions.openedStateMode",
            "name": "openedStateMode",
            "type": "string",
            "typesDescription": {
                "primitiveTypes": [
                    "string"
                ],
                "arrayTypes": []
            }
        },
        {
            "docID": "dxDrawerOptions.position",
            "name": "position",
            "type": "string",
            "typesDescription": {
                "primitiveTypes": [
                    "string"
                ],
                "arrayTypes": []
            }
        },
        {
            "docID": "dxDrawerOptions.revealMode",
            "name": "revealMode",
            "type": "string",
            "typesDescription": {
                "primitiveTypes": [
                    "string"
                ],
                "arrayTypes": []
            }
        },
        {
            "docID": "DOMComponentOptions.rtlEnabled",
            "name": "rtlEnabled",
            "type": "boolean",
            "typesDescription": {
                "primitiveTypes": [
                    "boolean"
                ],
                "arrayTypes": []
            }
        },
        {
            "docID": "dxDrawerOptions.shading",
            "name": "shading",
            "type": "boolean",
            "typesDescription": {
                "primitiveTypes": [
                    "boolean"
                ],
                "arrayTypes": []
            }
        },
        {
            "docID": "dxDrawerOptions.template",
            "name": "template",
            "type": "any",
            "typesDescription": {
                "primitiveTypes": [
                    "any"
                ],
                "arrayTypes": []
            }
        },
        {
            "docID": "WidgetOptions.visible",
            "name": "visible",
            "type": "boolean",
            "typesDescription": {
                "primitiveTypes": [
                    "boolean"
                ],
                "arrayTypes": []
            }
        },
        {
            "docID": "DOMComponentOptions.width",
            "name": "width",
            "type": "number | Function | string | undefined",
            "typesDescription": {
                "primitiveTypes": [
                    "number",
                    "Function",
                    "string",
                    "undefined"
                ],
                "arrayTypes": []
            }
        }
    ],
    "isEditor": false,
    "module": "devextreme/ui/drawer",
    "packageName": "devextreme-angular",
    "imports": [
        {
            "path": "devextreme/ui/drawer",
            "importString": "{ DisposingEvent, InitializedEvent, OptionChangedEvent }"
        }
    ],
    "nestedComponents": [],
    "renderReexports": true
}