{
    "docID": "dxLoadIndicator",
    "className": "DxLoadIndicator",
    "widgetName": "dxLoadIndicator",
    "isViz": false,
    "isExtension": false,
    "selector": "dx-load-indicator",
    "events": [
        {
            "docID": "dxLoadIndicatorOptions.onContentReady",
            "emit": "onContentReady",
            "subscribe": "contentReady",
            "type": "EventEmitter<ContentReadyEvent>"
        },
        {
            "docID": "dxLoadIndicatorOptions.onDisposing",
            "emit": "onDisposing",
            "subscribe": "disposing",
            "type": "EventEmitter<DisposingEvent>"
        },
        {
            "docID": "dxLoadIndicatorOptions.onInitialized",
            "emit": "onInitialized",
            "subscribe": "initialized",
            "type": "EventEmitter<InitializedEvent>"
        },
        {
            "docID": "dxLoadIndicatorOptions.onOptionChanged",
            "emit": "onOptionChanged",
            "subscribe": "optionChanged",
            "type": "EventEmitter<OptionChangedEvent>"
        },
        {
            "isInternal": true,
            "emit": "elementAttrChange",
            "type": "EventEmitter<any>"
        },
        {
            "isInternal": true,
            "emit": "heightChange",
            "type": "EventEmitter<number | Function | string | undefined>"
        },
        {
            "isInternal": true,
            "emit": "hintChange",
            "type": "EventEmitter<string | undefined>"
        },
        {
            "isInternal": true,
            "emit": "indicatorSrcChange",
            "type": "EventEmitter<string>"
        },
        {
            "isInternal": true,
            "emit": "rtlEnabledChange",
            "type": "EventEmitter<boolean>"
        },
        {
            "isInternal": true,
            "emit": "visibleChange",
            "type": "EventEmitter<boolean>"
        },
        {
            "isInternal": true,
            "emit": "widthChange",
            "type": "EventEmitter<number | Function | string | undefined>"
        }
    ],
    "properties": [
        {
            "docID": "DOMComponentOptions.elementAttr",
            "name": "elementAttr",
            "type": "any",
            "typesDescription": {
                "primitiveTypes": [
                    "any"
                ],
                "arrayTypes": []
            }
        },
        {
            "docID": "DOMComponentOptions.height",
            "name": "height",
            "type": "number | Function | string | undefined",
            "typesDescription": {
                "primitiveTypes": [
                    "number",
                    "Function",
                    "string",
                    "undefined"
                ],
                "arrayTypes": []
            }
        },
        {
            "docID": "WidgetOptions.hint",
            "name": "hint",
            "type": "string | undefined",
            "typesDescription": {
                "primitiveTypes": [
                    "string",
                    "undefined"
                ],
                "arrayTypes": []
            }
        },
        {
            "docID": "dxLoadIndicatorOptions.indicatorSrc",
            "name": "indicatorSrc",
            "type": "string",
            "typesDescription": {
                "primitiveTypes": [
                    "string"
                ],
                "arrayTypes": []
            }
        },
        {
            "docID": "DOMComponentOptions.rtlEnabled",
            "name": "rtlEnabled",
            "type": "boolean",
            "typesDescription": {
                "primitiveTypes": [
                    "boolean"
                ],
                "arrayTypes": []
            }
        },
        {
            "docID": "WidgetOptions.visible",
            "name": "visible",
            "type": "boolean",
            "typesDescription": {
                "primitiveTypes": [
                    "boolean"
                ],
                "arrayTypes": []
            }
        },
        {
            "docID": "DOMComponentOptions.width",
            "name": "width",
            "type": "number | Function | string | undefined",
            "typesDescription": {
                "primitiveTypes": [
                    "number",
                    "Function",
                    "string",
                    "undefined"
                ],
                "arrayTypes": []
            }
        }
    ],
    "isEditor": false,
    "module": "devextreme/ui/load_indicator",
    "packageName": "devextreme-angular",
    "imports": [
        {
            "path": "devextreme/ui/load_indicator",
            "importString": "{ ContentReadyEvent, DisposingEvent, InitializedEvent, OptionChangedEvent }"
        }
    ],
    "nestedComponents": [],
    "renderReexports": true
}