{
    "docID": "dxGanttOptions.scaleTypeRange",
    "className": "DxoScaleTypeRange",
    "selector": "dxo-scale-type-range",
    "optionName": "scaleTypeRange",
    "properties": [
        {
            "docID": "dxGanttOptions.scaleTypeRange.max",
            "name": "max",
            "type": "string",
            "typesDescription": {
                "primitiveTypes": [
                    "string"
                ],
                "arrayTypes": []
            }
        },
        {
            "docID": "dxGanttOptions.scaleTypeRange.min",
            "name": "min",
            "type": "string",
            "typesDescription": {
                "primitiveTypes": [
                    "string"
                ],
                "arrayTypes": []
            }
        }
    ],
    "path": "scale-type-range",
    "propertyName": "scaleTypeRange",
    "collectionNestedComponents": [],
    "options": [
        {
            "PrimitiveTypes": [
                "string"
            ],
            "DocID": "dxGanttOptions.scaleTypeRange.max"
        },
        {
            "PrimitiveTypes": [
                "string"
            ],
            "DocID": "dxGanttOptions.scaleTypeRange.min"
        }
    ],
    "baseClass": "NestedOption",
    "basePath": "devextreme-angular/core",
    "hasSimpleBaseClass": true
}