{
    "docID": "dxChartOptions.commonAxisSettings.tick",
    "className": "DxoTick",
    "selector": "dxo-tick",
    "optionName": "tick",
    "properties": [
        {
            "docID": "dxChartOptions.commonAxisSettings.tick.color",
            "name": "color",
            "type": "string",
            "typesDescription": {
                "primitiveTypes": [
                    "string"
                ],
                "arrayTypes": []
            }
        },
        {
            "docID": "dxChartOptions.commonAxisSettings.tick.length",
            "name": "length",
            "type": "number",
            "typesDescription": {
                "primitiveTypes": [
                    "number"
                ],
                "arrayTypes": []
            }
        },
        {
            "docID": "dxChartOptions.commonAxisSettings.tick.opacity",
            "name": "opacity",
            "type": "number | undefined",
            "typesDescription": {
                "primitiveTypes": [
                    "number",
                    "undefined"
                ],
                "arrayTypes": []
            }
        },
        {
            "docID": "dxChartOptions.commonAxisSettings.tick.shift",
            "name": "shift",
            "type": "number",
            "typesDescription": {
                "primitiveTypes": [
                    "number"
                ],
                "arrayTypes": []
            }
        },
        {
            "docID": "dxChartOptions.commonAxisSettings.tick.visible",
            "name": "visible",
            "type": "boolean",
            "typesDescription": {
                "primitiveTypes": [
                    "boolean"
                ],
                "arrayTypes": []
            }
        },
        {
            "docID": "dxChartOptions.commonAxisSettings.tick.width",
            "name": "width",
            "type": "number",
            "typesDescription": {
                "primitiveTypes": [
                    "number"
                ],
                "arrayTypes": []
            }
        }
    ],
    "path": "tick",
    "propertyName": "tick",
    "collectionNestedComponents": [],
    "options": [
        {
            "PrimitiveTypes": [
                "string"
            ],
            "DocID": "dxChartOptions.commonAxisSettings.tick.color"
        },
        {
            "PrimitiveTypes": [
                "number"
            ],
            "DocID": "dxChartOptions.commonAxisSettings.tick.length"
        },
        {
            "PrimitiveTypes": [
                "number",
                "undefined"
            ],
            "DocID": "dxChartOptions.commonAxisSettings.tick.opacity"
        },
        {
            "PrimitiveTypes": [
                "number"
            ],
            "DocID": "dxChartOptions.commonAxisSettings.tick.shift"
        },
        {
            "PrimitiveTypes": [
                "boolean"
            ],
            "DocID": "dxChartOptions.commonAxisSettings.tick.visible"
        },
        {
            "PrimitiveTypes": [
                "number"
            ],
            "DocID": "dxChartOptions.commonAxisSettings.tick.width"
        },
        {
            "PrimitiveTypes": [
                "string"
            ],
            "DocID": "dxChartOptions.commonAxisSettings.tick.color"
        },
        {
            "PrimitiveTypes": [
                "number"
            ],
            "DocID": "dxChartOptions.commonAxisSettings.tick.length"
        },
        {
            "PrimitiveTypes": [
                "number",
                "undefined"
            ],
            "DocID": "dxChartOptions.commonAxisSettings.tick.opacity"
        },
        {
            "PrimitiveTypes": [
                "number"
            ],
            "DocID": "dxChartOptions.commonAxisSettings.tick.shift"
        },
        {
            "PrimitiveTypes": [
                "boolean"
            ],
            "DocID": "dxChartOptions.commonAxisSettings.tick.visible"
        },
        {
            "PrimitiveTypes": [
                "number"
            ],
            "DocID": "dxChartOptions.commonAxisSettings.tick.width"
        },
        {
            "PrimitiveTypes": [
                "string"
            ],
            "DocID": "dxChartOptions.commonAxisSettings.tick.color"
        },
        {
            "PrimitiveTypes": [
                "number"
            ],
            "DocID": "dxChartOptions.commonAxisSettings.tick.length"
        },
        {
            "PrimitiveTypes": [
                "number",
                "undefined"
            ],
            "DocID": "dxChartOptions.commonAxisSettings.tick.opacity"
        },
        {
            "PrimitiveTypes": [
                "number"
            ],
            "DocID": "dxChartOptions.commonAxisSettings.tick.shift"
        },
        {
            "PrimitiveTypes": [
                "boolean"
            ],
            "DocID": "dxChartOptions.commonAxisSettings.tick.visible"
        },
        {
            "PrimitiveTypes": [
                "number"
            ],
            "DocID": "dxChartOptions.commonAxisSettings.tick.width"
        },
        {
            "PrimitiveTypes": [
                "string"
            ],
            "DocID": "BaseGaugeOptions.scale.tick.color"
        },
        {
            "PrimitiveTypes": [
                "number"
            ],
            "DocID": "BaseGaugeOptions.scale.tick.length"
        },
        {
            "PrimitiveTypes": [
                "number"
            ],
            "DocID": "BaseGaugeOptions.scale.tick.opacity"
        },
        {
            "PrimitiveTypes": [
                "boolean"
            ],
            "DocID": "BaseGaugeOptions.scale.tick.visible"
        },
        {
            "PrimitiveTypes": [
                "number"
            ],
            "DocID": "BaseGaugeOptions.scale.tick.width"
        },
        {
            "PrimitiveTypes": [
                "string"
            ],
            "DocID": "BaseGaugeOptions.scale.tick.color"
        },
        {
            "PrimitiveTypes": [
                "number"
            ],
            "DocID": "BaseGaugeOptions.scale.tick.length"
        },
        {
            "PrimitiveTypes": [
                "number"
            ],
            "DocID": "BaseGaugeOptions.scale.tick.opacity"
        },
        {
            "PrimitiveTypes": [
                "boolean"
            ],
            "DocID": "BaseGaugeOptions.scale.tick.visible"
        },
        {
            "PrimitiveTypes": [
                "number"
            ],
            "DocID": "BaseGaugeOptions.scale.tick.width"
        },
        {
            "PrimitiveTypes": [
                "string"
            ],
            "DocID": "dxPolarChartOptions.commonAxisSettings.tick.color"
        },
        {
            "PrimitiveTypes": [
                "number"
            ],
            "DocID": "dxPolarChartOptions.commonAxisSettings.tick.length"
        },
        {
            "PrimitiveTypes": [
                "number",
                "undefined"
            ],
            "DocID": "dxPolarChartOptions.commonAxisSettings.tick.opacity"
        },
        {
            "PrimitiveTypes": [
                "number"
            ],
            "DocID": "dxPolarChartOptions.argumentAxis.tick.shift"
        },
        {
            "PrimitiveTypes": [
                "boolean"
            ],
            "DocID": "dxPolarChartOptions.commonAxisSettings.tick.visible"
        },
        {
            "PrimitiveTypes": [
                "number"
            ],
            "DocID": "dxPolarChartOptions.commonAxisSettings.tick.width"
        },
        {
            "PrimitiveTypes": [
                "string"
            ],
            "DocID": "dxPolarChartOptions.commonAxisSettings.tick.color"
        },
        {
            "PrimitiveTypes": [
                "number"
            ],
            "DocID": "dxPolarChartOptions.commonAxisSettings.tick.length"
        },
        {
            "PrimitiveTypes": [
                "number",
                "undefined"
            ],
            "DocID": "dxPolarChartOptions.commonAxisSettings.tick.opacity"
        },
        {
            "PrimitiveTypes": [
                "boolean"
            ],
            "DocID": "dxPolarChartOptions.commonAxisSettings.tick.visible"
        },
        {
            "PrimitiveTypes": [
                "number"
            ],
            "DocID": "dxPolarChartOptions.commonAxisSettings.tick.width"
        },
        {
            "PrimitiveTypes": [
                "string"
            ],
            "DocID": "dxPolarChartOptions.commonAxisSettings.tick.color"
        },
        {
            "PrimitiveTypes": [
                "number"
            ],
            "DocID": "dxPolarChartOptions.commonAxisSettings.tick.length"
        },
        {
            "PrimitiveTypes": [
                "number",
                "undefined"
            ],
            "DocID": "dxPolarChartOptions.commonAxisSettings.tick.opacity"
        },
        {
            "PrimitiveTypes": [
                "boolean"
            ],
            "DocID": "dxPolarChartOptions.valueAxis.tick.visible"
        },
        {
            "PrimitiveTypes": [
                "number"
            ],
            "DocID": "dxPolarChartOptions.commonAxisSettings.tick.width"
        },
        {
            "PrimitiveTypes": [
                "string"
            ],
            "DocID": "dxRangeSelectorOptions.scale.tick.color"
        },
        {
            "PrimitiveTypes": [
                "number"
            ],
            "DocID": "dxRangeSelectorOptions.scale.tick.opacity"
        },
        {
            "PrimitiveTypes": [
                "number"
            ],
            "DocID": "dxRangeSelectorOptions.scale.tick.width"
        }
    ],
    "baseClass": "NestedOption",
    "basePath": "devextreme-angular/core",
    "hasSimpleBaseClass": true
}