{
    "properties": [
        {
            "docID": "dxFilterBuilderField.calculateFilterExpression",
            "name": "calculateFilterExpression",
            "type": "Function",
            "typesDescription": {
                "primitiveTypes": [
                    "Function"
                ],
                "arrayTypes": []
            }
        },
        {
            "docID": "dxFilterBuilderField.caption",
            "name": "caption",
            "type": "string | undefined",
            "typesDescription": {
                "primitiveTypes": [
                    "string",
                    "undefined"
                ],
                "arrayTypes": []
            }
        },
        {
            "docID": "dxFilterBuilderField.customizeText",
            "name": "customizeText",
            "type": "Function",
            "typesDescription": {
                "primitiveTypes": [
                    "Function"
                ],
                "arrayTypes": []
            }
        },
        {
            "docID": "dxFilterBuilderField.dataField",
            "name": "dataField",
            "type": "string | undefined",
            "typesDescription": {
                "primitiveTypes": [
                    "string",
                    "undefined"
                ],
                "arrayTypes": []
            }
        },
        {
            "docID": "dxFilterBuilderField.dataType",
            "name": "dataType",
            "type": "string",
            "typesDescription": {
                "primitiveTypes": [
                    "string"
                ],
                "arrayTypes": []
            }
        },
        {
            "docID": "dxFilterBuilderField.editorOptions",
            "name": "editorOptions",
            "type": "any",
            "typesDescription": {
                "primitiveTypes": [
                    "any"
                ],
                "arrayTypes": []
            }
        },
        {
            "docID": "dxFilterBuilderField.editorTemplate",
            "name": "editorTemplate",
            "type": "any",
            "typesDescription": {
                "primitiveTypes": [
                    "any"
                ],
                "arrayTypes": []
            }
        },
        {
            "docID": "dxFilterBuilderField.falseText",
            "name": "falseText",
            "type": "string",
            "typesDescription": {
                "primitiveTypes": [
                    "string"
                ],
                "arrayTypes": []
            }
        },
        {
            "docID": "dxFilterBuilderField.filterOperations",
            "name": "filterOperations",
            "type": "Array<string>",
            "typesDescription": {
                "primitiveTypes": [],
                "arrayTypes": [
                    "string"
                ]
            },
            "isCollection": true
        },
        {
            "docID": "dxFilterBuilderField.format",
            "name": "format",
            "type": "Format | string | format",
            "typesDescription": {
                "primitiveTypes": [
                    "Format",
                    "string",
                    "format"
                ],
                "arrayTypes": []
            }
        },
        {
            "docID": "dxFilterBuilderField.lookup",
            "name": "lookup",
            "type": "{ allowClearing?: boolean, dataSource?: DataSourceOptions | Store | undefined | Array<any>, displayExpr?: Function | string | undefined, valueExpr?: Function | string | undefined }",
            "typesDescription": {
                "primitiveTypes": [
                    "{ allowClearing?: boolean, dataSource?: DataSourceOptions | Store | undefined | Array<any>, displayExpr?: Function | string | undefined, valueExpr?: Function | string | undefined }"
                ],
                "arrayTypes": []
            }
        },
        {
            "docID": "dxFilterBuilderField.name",
            "name": "name",
            "type": "string | undefined",
            "typesDescription": {
                "primitiveTypes": [
                    "string",
                    "undefined"
                ],
                "arrayTypes": []
            }
        },
        {
            "docID": "dxFilterBuilderField.trueText",
            "name": "trueText",
            "type": "string",
            "typesDescription": {
                "primitiveTypes": [
                    "string"
                ],
                "arrayTypes": []
            }
        },
        {
            "name": "allowCrossGroupCalculation",
            "type": "boolean",
            "typesDescription": {
                "primitiveTypes": [
                    "boolean"
                ],
                "arrayTypes": []
            }
        },
        {
            "name": "allowExpandAll",
            "type": "boolean",
            "typesDescription": {
                "primitiveTypes": [
                    "boolean"
                ],
                "arrayTypes": []
            }
        },
        {
            "name": "allowFiltering",
            "type": "boolean",
            "typesDescription": {
                "primitiveTypes": [
                    "boolean"
                ],
                "arrayTypes": []
            }
        },
        {
            "name": "allowSorting",
            "type": "boolean",
            "typesDescription": {
                "primitiveTypes": [
                    "boolean"
                ],
                "arrayTypes": []
            }
        },
        {
            "name": "allowSortingBySummary",
            "type": "boolean",
            "typesDescription": {
                "primitiveTypes": [
                    "boolean"
                ],
                "arrayTypes": []
            }
        },
        {
            "name": "area",
            "type": "string",
            "typesDescription": {
                "primitiveTypes": [
                    "string"
                ],
                "arrayTypes": []
            }
        },
        {
            "name": "areaIndex",
            "type": "number",
            "typesDescription": {
                "primitiveTypes": [
                    "number"
                ],
                "arrayTypes": []
            }
        },
        {
            "name": "calculateCustomSummary",
            "type": "Function",
            "typesDescription": {
                "primitiveTypes": [
                    "Function"
                ],
                "arrayTypes": []
            }
        },
        {
            "name": "calculateSummaryValue",
            "type": "Function",
            "typesDescription": {
                "primitiveTypes": [
                    "Function"
                ],
                "arrayTypes": []
            }
        },
        {
            "name": "displayFolder",
            "type": "string",
            "typesDescription": {
                "primitiveTypes": [
                    "string"
                ],
                "arrayTypes": []
            }
        },
        {
            "name": "expanded",
            "type": "boolean",
            "typesDescription": {
                "primitiveTypes": [
                    "boolean"
                ],
                "arrayTypes": []
            }
        },
        {
            "name": "filterType",
            "type": "string",
            "typesDescription": {
                "primitiveTypes": [
                    "string"
                ],
                "arrayTypes": []
            }
        },
        {
            "name": "filterValues",
            "type": "Array<any>",
            "typesDescription": {
                "primitiveTypes": [],
                "arrayTypes": [
                    "any"
                ]
            },
            "isCollection": true
        },
        {
            "name": "groupIndex",
            "type": "number",
            "typesDescription": {
                "primitiveTypes": [
                    "number"
                ],
                "arrayTypes": []
            }
        },
        {
            "name": "groupInterval",
            "type": "number | string",
            "typesDescription": {
                "primitiveTypes": [
                    "number",
                    "string"
                ],
                "arrayTypes": []
            }
        },
        {
            "name": "groupName",
            "type": "string",
            "typesDescription": {
                "primitiveTypes": [
                    "string"
                ],
                "arrayTypes": []
            }
        },
        {
            "name": "headerFilter",
            "type": "{ allowSearch?: boolean, height?: number, width?: number }",
            "typesDescription": {
                "primitiveTypes": [
                    "{ allowSearch?: boolean, height?: number, width?: number }"
                ],
                "arrayTypes": []
            }
        },
        {
            "name": "isMeasure",
            "type": "boolean",
            "typesDescription": {
                "primitiveTypes": [
                    "boolean"
                ],
                "arrayTypes": []
            }
        },
        {
            "isDeprecated": true,
            "name": "precision",
            "type": "number",
            "typesDescription": {
                "primitiveTypes": [
                    "number"
                ],
                "arrayTypes": []
            }
        },
        {
            "name": "runningTotal",
            "type": "string",
            "typesDescription": {
                "primitiveTypes": [
                    "string"
                ],
                "arrayTypes": []
            }
        },
        {
            "name": "selector",
            "type": "Function",
            "typesDescription": {
                "primitiveTypes": [
                    "Function"
                ],
                "arrayTypes": []
            }
        },
        {
            "name": "showGrandTotals",
            "type": "boolean",
            "typesDescription": {
                "primitiveTypes": [
                    "boolean"
                ],
                "arrayTypes": []
            }
        },
        {
            "name": "showTotals",
            "type": "boolean",
            "typesDescription": {
                "primitiveTypes": [
                    "boolean"
                ],
                "arrayTypes": []
            }
        },
        {
            "name": "showValues",
            "type": "boolean",
            "typesDescription": {
                "primitiveTypes": [
                    "boolean"
                ],
                "arrayTypes": []
            }
        },
        {
            "name": "sortBy",
            "type": "string",
            "typesDescription": {
                "primitiveTypes": [
                    "string"
                ],
                "arrayTypes": []
            }
        },
        {
            "name": "sortBySummaryField",
            "type": "string",
            "typesDescription": {
                "primitiveTypes": [
                    "string"
                ],
                "arrayTypes": []
            }
        },
        {
            "name": "sortBySummaryPath",
            "type": "Array<number | string>",
            "typesDescription": {
                "primitiveTypes": [],
                "arrayTypes": [
                    "number",
                    "string"
                ]
            },
            "isCollection": true
        },
        {
            "name": "sortingMethod",
            "type": "Function",
            "typesDescription": {
                "primitiveTypes": [
                    "Function"
                ],
                "arrayTypes": []
            }
        },
        {
            "name": "sortOrder",
            "type": "string",
            "typesDescription": {
                "primitiveTypes": [
                    "string"
                ],
                "arrayTypes": []
            }
        },
        {
            "name": "summaryDisplayMode",
            "type": "string",
            "typesDescription": {
                "primitiveTypes": [
                    "string"
                ],
                "arrayTypes": []
            }
        },
        {
            "name": "summaryType",
            "type": "string",
            "typesDescription": {
                "primitiveTypes": [
                    "string"
                ],
                "arrayTypes": []
            }
        },
        {
            "name": "visible",
            "type": "boolean",
            "typesDescription": {
                "primitiveTypes": [
                    "boolean"
                ],
                "arrayTypes": []
            }
        },
        {
            "name": "width",
            "type": "number",
            "typesDescription": {
                "primitiveTypes": [
                    "number"
                ],
                "arrayTypes": []
            }
        },
        {
            "name": "wordWrapEnabled",
            "type": "boolean",
            "typesDescription": {
                "primitiveTypes": [
                    "boolean"
                ],
                "arrayTypes": []
            }
        }
    ],
    "events": [],
    "className": "DxiFilterBuilderField",
    "path": "filter-builder-field-dxi",
    "baseClass": "CollectionNestedOption",
    "basePath": "devextreme-angular/core",
    "imports": [
        {
            "path": "devextreme/data",
            "importString": "{ Store }"
        },
        {
            "path": "devextreme/data/data_source",
            "importString": "{ Options as DataSourceOptions }"
        },
        {
            "path": "devextreme/localization",
            "importString": "{ Format }"
        },
        {
            "path": "devextreme/ui/widget/ui.widget",
            "importString": "{ format }"
        }
    ]
}